random_color_hex/ColorCalculus.py
random_color_hex/__init__.py
random_color_hex/__main__.py
random_color_hex/random_color_hex.py
random_color_hex-2.1.6.dist-info/licenses/LICENSE.txt
random_color_hex-2.1.6.dist-info/METADATA
random_color_hex-2.1.6.dist-info/WHEEL
random_color_hex-2.1.6.dist-info/top_level.txt
random_color_hex-2.1.6.dist-info/RECORD
